{
	"active": [
		{
			"name": "마지막 임무",
			"damage": 4058032,
			"coolTime": 290,
			"requireLv": 100,
			"gapLv": 5,
			"maxLv": 2,
			"nowLv": 2,
			"maxTp": 0.0,
			"nowTp": 0.0,
			"delay": 6,
			"talisman": null
		},
		{
			"name": "월식",
			"damage": 2183181,
			"coolTime": 180,
			"requireLv": 85,
			"gapLv": 5,
			"maxLv": 5,
			"nowLv": 5,
			"maxTp": 0.0,
			"nowTp": 0.0,
			"delay": 3,
			"talisman": null
		},
		{
			"name": "요인 암살",
			"damage": 1916469,
			"coolTime": 145,
			"requireLv": 50,
			"gapLv": 5,
			"maxLv": 12,
			"nowLv": 0,
			"maxTp": 0.0,
			"nowTp": 0.0,
			"delay": 2,
			"talisman": null
		},
		{
			"name": "지고 뜨는 달",
			"damage": 1453115,
			"coolTime": 60,
			"requireLv": 95,
			"gapLv": 2,
			"maxLv": 6,
			"nowLv": 6,
			"maxTp": 0.0,
			"nowTp": 0.0,
			"delay": 1.5,
			"talisman": null
		},
		{
			"name": "블레이드 팰컨",
			"damage": 1382868,
			"coolTime": 45,
			"requireLv": 45,
			"gapLv": 2,
			"maxLv": 31,
			"nowLv": 31,
			"maxTp": 5.0,
			"nowTp": 5.0,
			"delay": 0.5,
			"talisman": {
				"name": "블레이드 스웜프",
				"damage": 1726577,
				"coolTime": 45,
				"available": 0,
				"rune": 0
			}
		},
		{
			"name": "월광진혼곡",
			"damage": 1248542,
			"coolTime": 40,
			"requireLv": 75,
			"gapLv": 2,
			"maxLv": 16,
			"nowLv": 16,
			"maxTp": 0.0,
			"nowTp": 0.0,
			"delay": 1.5,
			"talisman": {
				"name": "죽음의 올가미",
				"damage": 1611040,
				"coolTime": 40,
				"available": 3,
				"rune": 0
			}
		},
		{
			"name": "문페이즈",
			"damage": 1177663,
			"coolTime": 50,
			"requireLv": 70,
			"gapLv": 2,
			"maxLv": 18,
			"nowLv": 18,
			"maxTp": 5.0,
			"nowTp": 5.0,
			"delay": 1,
			"talisman": {
				"name": "슈퍼문 페이즈 쉬프트",
				"damage": 1507409,
				"coolTime": 45,
				"available": 0,
				"rune": 0
			}
		},
		{
			"name": "섬멸",
			"damage": 1140763,
			"coolTime": 45,
			"requireLv": 80,
			"gapLv": 2,
			"maxLv": 13,
			"nowLv": 13,
			"maxTp": 0.0,
			"nowTp": 0.0,
			"delay": 1,
			"talisman": {
				"name": "임무 - 인멸",
				"damage": 1517214,
				"coolTime": 45,
				"available": 0,
				"rune": 0
			}
		},
		{
			"name": "목표포착",
			"damage": 859167,
			"coolTime": 30,
			"requireLv": 60,
			"gapLv": 2,
			"maxLv": 23,
			"nowLv": 23,
			"maxTp": 5.0,
			"nowTp": 5.0,
			"delay": 1,
			"talisman": {
				"name": "엑스트라 듀티",
				"damage": 1146129,
				"coolTime": 27,
				"available": 2,
				"rune": 0
			}
		},
		{
			"name": "암월비보",
			"damage": 812896,
			"coolTime": 20,
			"requireLv": 35,
			"gapLv": 2,
			"maxLv": 36,
			"nowLv": 36,
			"maxTp": 5.0,
			"nowTp": 5.0,
			"delay": 1,
			"talisman": {
				"name": "잠행의 정수",
				"damage": 1032378,
				"coolTime": 17,
				"available": 1,
				"rune": 1
			}
		},
		{
			"name": "목표 사격",
			"damage": 791730,
			"coolTime": 20,
			"requireLv": 40,
			"gapLv": 2,
			"maxLv": 33,
			"nowLv": 33,
			"maxTp": 5.0,
			"nowTp": 5.0,
			"delay": 1,
			"talisman": {
				"name": "임무 - 목표 말살",
				"damage": 1353859,
				"coolTime": 20,
				"available": 0,
				"rune": 0
			}
		},
		{
			"name": "보름달 베기",
			"damage": 482695,
			"coolTime": 15,
			"requireLv": 35,
			"gapLv": 2,
			"maxLv": 36,
			"nowLv": 0,
			"maxTp": 5.0,
			"nowTp": 0.0,
			"delay": 0.3,
			"talisman": null
		},
		{
			"name": "조준 사격",
			"damage": 320926,
			"coolTime": 8,
			"requireLv": 30,
			"gapLv": 2,
			"maxLv": 38,
			"nowLv": 38,
			"maxTp": 5.0,
			"nowTp": 1.0,
			"delay": 0.3,
			"talisman": null
		},
		{
			"name": "달빛 가르기",
			"damage": 258946,
			"coolTime": 7,
			"requireLv": 25,
			"gapLv": 2,
			"maxLv": 41,
			"nowLv": 0,
			"maxTp": 5.0,
			"nowTp": 0.0,
			"delay": 0.3,
			"talisman": null
		},
		{
			"name": "연속 사격",
			"damage": 206221,
			"coolTime": 6,
			"requireLv": 15,
			"gapLv": 2,
			"maxLv": 46,
			"nowLv": 0,
			"maxTp": 5.0,
			"nowTp": 0.0,
			"delay": 0.3,
			"talisman": null
		},
		{
			"name": "쌍현참",
			"damage": 195860,
			"coolTime": 6,
			"requireLv": 20,
			"gapLv": 2,
			"maxLv": 43,
			"nowLv": 0,
			"maxTp": 5.0,
			"nowTp": 0.0,
			"delay": 0.1,
			"talisman": null
		},
		{
			"name": "로망 대시",
			"damage": 183134,
			"coolTime": 5,
			"requireLv": 15,
			"gapLv": 2,
			"maxLv": 46,
			"nowLv": 0,
			"maxTp": 5.0,
			"nowTp": 0.0,
			"delay": 0.3,
			"talisman": null
		},
		{
			"name": "뒷목 가격",
			"damage": 127765,
			"coolTime": 6,
			"requireLv": 10,
			"gapLv": 2,
			"maxLv": 48,
			"nowLv": 0,
			"maxTp": 4.0,
			"nowTp": 0.0,
			"delay": 0.3,
			"talisman": null
		},
		{
			"name": "평타(1사이클)",
			"damage": 69202,
			"coolTime": 0,
			"requireLv": 1,
			"gapLv": 1,
			"maxLv": 100,
			"nowLv": 100,
			"maxTp": 3.0,
			"nowTp": 1.0,
			"delay": 1,
			"cool_fix": true,
			"talisman": null
		}
	],
	"passive": [
		{
			"name": "요원의 전투술",
			"requireLv": 15,
			"maxValue": 30.0,
			"upValue": 2.0,
			"type": "DAMAGE",
			"target": "ALL",
			"requirementType": null,
			"requirementValue": null
		},
		{
			"name": "소태도 마스터리",
			"requireLv": 20,
			"maxValue": 21.0,
			"upValue": 2.0,
			"type": "DAMAGE",
			"target": "ALL",
			"requirementType": "WEAPON",
			"requirementValue": "소태도"
		},
		{
			"name": "결의",
			"requireLv": 48,
			"maxValue": 42.5,
			"upValue": 2.0,
			"type": "DAMAGE",
			"target": "ALL",
			"requirementType": null,
			"requirementValue": null
		},
		{
			"name": "냉혈",
			"requireLv": 75,
			"maxValue": 46.0,
			"upValue": 2.0,
			"type": "DAMAGE",
			"target": "ALL",
			"requirementType": null,
			"requirementValue": null
		},
		{
			"name": "무결",
			"requireLv": 95,
			"maxValue": 26.0,
			"upValue": 2.0,
			"type": "DAMAGE",
			"target": "ALL",
			"requirementType": null,
			"requirementValue": null
		}
	],
	"special": [],
	"weapon": [
		{
			"type": "소태도",
			"damage": 1.0,
			"coolTime": 1.0
		},
		{
			"type": "중검",
			"damage": 0.870328384407226,
			"coolTime": 1.1
		},
		{
			"type": "장도",
			"damage": 0.8439651052235012,
			"coolTime": 1.05
		},
		{
			"type": "코어블레이드",
			"damage": 0.8153907123017864,
			"coolTime": 0.95
		},
		{
			"type": "공통",
			"damage": 1.0,
			"coolTime": 1.0
		}
	]
}